pytest_checkers/__init__.py
pytest_checkers/checkers.py
pytest_checkers/py.typed
pytest_checkers-1.0.3.dist-info/WHEEL
pytest_checkers-1.0.3.dist-info/entry_points.txt
pytest_checkers-1.0.3.dist-info/METADATA
pytest_checkers-1.0.3.dist-info/RECORD
