Metadata-Version: 2.3
Name: pytest-checkers
Version: 1.0.3
Summary: Pytest Plugin for dry-run checks LSPs, Type Checkers, Linters, and Formatters during testing
Author: the-citto
Classifier: License :: OSI Approved :: MIT License
Classifier: Operating System :: POSIX :: Linux
Classifier: Operating System :: Microsoft :: Windows
Classifier: Programming Language :: Python
Classifier: Programming Language :: Python :: 3.13
Classifier: Programming Language :: Python :: 3.14
Classifier: Typing :: Typed
Requires-Dist: pytest>=9.0.2
Requires-Dist: pytest-checkers[black] ; extra == 'all'
Requires-Dist: pytest-checkers[flake8] ; extra == 'all'
Requires-Dist: pytest-checkers[isort] ; extra == 'all'
Requires-Dist: pytest-checkers[mypy] ; extra == 'all'
Requires-Dist: pytest-checkers[pyright] ; extra == 'all'
Requires-Dist: pytest-checkers[ruff] ; extra == 'all'
Requires-Dist: pytest-checkers[ty] ; extra == 'all'
Requires-Dist: black>=25.12.0 ; extra == 'black'
Requires-Dist: flake8>=7.3.0 ; extra == 'flake8'
Requires-Dist: isort[colors]>=7.0.0 ; extra == 'isort'
Requires-Dist: mypy>=1.19.0 ; extra == 'mypy'
Requires-Dist: pyright[nodejs]>=1.1.407 ; extra == 'pyright'
Requires-Dist: ruff>=0.14.8 ; extra == 'ruff'
Requires-Dist: ty>=0.0.1a33 ; extra == 'ty'
Requires-Python: >=3.13
Provides-Extra: all
Provides-Extra: black
Provides-Extra: flake8
Provides-Extra: isort
Provides-Extra: mypy
Provides-Extra: pyright
Provides-Extra: ruff
Provides-Extra: ty
